xtquantai/__init__.py
xtquantai/server.py
xtquantai-0.1.0.dist-info/METADATA
xtquantai-0.1.0.dist-info/WHEEL
xtquantai-0.1.0.dist-info/entry_points.txt
xtquantai-0.1.0.dist-info/licenses/LICENSE
xtquantai-0.1.0.dist-info/RECORD
