Metadata-Version: 2.4
Name: xtquantai
Version: 0.1.0
Summary: AI know use xtquant to do quantative project.
Author-email: davidfnck <davidfnck@gmail.com>
License-File: LICENSE
Requires-Python: >=3.11
Requires-Dist: anyio>=3.0.0
Requires-Dist: mcp>=1.3.0
Requires-Dist: xtquant
